MANIFEST.in
README.rst
setup.py
docs/HISTORY.txt
docs/LICENSE.GPL
docs/LICENSE.txt
simplelayout/__init__.py
simplelayout.types.news.egg-info/PKG-INFO
simplelayout.types.news.egg-info/SOURCES.txt
simplelayout.types.news.egg-info/dependency_links.txt
simplelayout.types.news.egg-info/entry_points.txt
simplelayout.types.news.egg-info/namespace_packages.txt
simplelayout.types.news.egg-info/not-zip-safe
simplelayout.types.news.egg-info/requires.txt
simplelayout.types.news.egg-info/top_level.txt
simplelayout/types/__init__.py
simplelayout/types/news/__init__.py
simplelayout/types/news/config.py
simplelayout/types/news/configure.zcml
simplelayout/types/news/dependencies.zcml
simplelayout/types/news/interfaces.py
simplelayout/types/news/news.py
simplelayout/types/news/newsfolder.py
simplelayout/types/news/upgrades.zcml
simplelayout/types/news/vocabularies.py
simplelayout/types/news/browser/__init__.py
simplelayout/types/news/browser/configure.zcml
simplelayout/types/news/browser/news_block_view.pt
simplelayout/types/news/browser/news_block_view.py
simplelayout/types/news/browser/news_result.pt
simplelayout/types/news/browser/news_topic_listing.pt
simplelayout/types/news/browser/news_topic_listing.py
simplelayout/types/news/browser/newslisting.pt
simplelayout/types/news/browser/newslisting.py
simplelayout/types/news/browser/newslisting_rss.pt
simplelayout/types/news/locales/plone.pot
simplelayout/types/news/locales/simplelayout.pot
simplelayout/types/news/locales/simplelayout.types.news.pot
simplelayout/types/news/locales/de/LC_MESSAGES/plone.po
simplelayout/types/news/locales/de/LC_MESSAGES/simplelayout.types.news.po
simplelayout/types/news/portlets/__init__.py
simplelayout/types/news/portlets/configure.zcml
simplelayout/types/news/portlets/news_portlet.pt
simplelayout/types/news/portlets/news_portlet.py
simplelayout/types/news/profiles/default/factorytool.xml
simplelayout/types/news/profiles/default/metadata.xml
simplelayout/types/news/profiles/default/portlets.xml
simplelayout/types/news/profiles/default/rolemap.xml
simplelayout/types/news/profiles/default/types.xml
simplelayout/types/news/profiles/default/types/News.xml
simplelayout/types/news/profiles/default/types/NewsFolder.xml
simplelayout/types/news/profiles/default/types/Topic.xml
simplelayout/types/news/profiles/newsfolder/factorytool.xml
