Metadata-Version: 1.1
Name: simplelayout.types.news
Version: 1.2.2
Summary: UNKNOWN
Home-page: https://github.com/4teamwork/simplelayout.types.news
Author: 4teamwork GmbH
Author-email: mailto:info@4teamwork.ch
License: GPL2
Platform: UNKNOWN
Classifier: Framework :: Plone
Classifier: Framework :: Plone :: 4.1
Classifier: Framework :: Plone :: 4.2
Classifier: Programming Language :: Python
Classifier: Topic :: Software Development :: Libraries :: Python Modules
